turpitude/__init__.py
turpitude/models/__init__.py
turpitude/models/inspection_report.py
turpitude-0.8.0.dist-info/METADATA
turpitude-0.8.0.dist-info/WHEEL
turpitude-0.8.0.dist-info/top_level.txt
turpitude-0.8.0.dist-info/RECORD
