Metadata-Version: 2.4
Name: turpitude
Version: 0.8.0
Summary: Internal Python package hosting no bullshit
Author: somebody
Project-URL: Homepage, https://github.com/nobodyy-nowhere
Classifier: Programming Language :: Python :: 3
Classifier: Operating System :: OS Independent
Requires-Python: >=3.9
Requires-Dist: pydantic>=2.10.6
